{"name":"Search in google","id":"validate-the-google-search-engine;search-in-google","testSteps":[{"number":1,"description":"Given the user open the URL \"https://www.google.com/\"","duration":3250,"startTime":"2024-04-03T07:50:21.304977400-05:00[America/Bogota]","precondition":false,"level":0,"children":[{"number":2,"description":"User opens the browser at https://www.google.com/","duration":2755,"startTime":"2024-04-03T07:50:21.798954400-05:00[America/Bogota]","exception":{"errorType":"net.thucydides.core.webdriver.DriverConfigurationError","message":"Could not instantiate class org.openqa.selenium.chrome.ChromeDriver","stackTrace":[{"declaringClass":"iteractions.NavigateTo","methodName":"performAs","fileName":"NavigateTo.java","lineNumber":16},{"declaringClass":"stepdefinitions.GoogleSearchStepDefinition","methodName":"theUserOpenTheURL","fileName":"GoogleSearchStepDefinition.java","lineNumber":25},{"declaringClass":"io.cucumber.java.Invoker","methodName":"doInvoke","fileName":"Invoker.java","lineNumber":66},{"declaringClass":"io.cucumber.java.Invoker","methodName":"invoke","fileName":"Invoker.java","lineNumber":24},{"declaringClass":"io.cucumber.java.AbstractGlueDefinition","methodName":"invokeMethod","fileName":"AbstractGlueDefinition.java","lineNumber":47},{"declaringClass":"io.cucumber.java.JavaStepDefinition","methodName":"execute","fileName":"JavaStepDefinition.java","lineNumber":29},{"declaringClass":"io.cucumber.core.runner.CoreStepDefinition","methodName":"execute","fileName":"CoreStepDefinition.java","lineNumber":66},{"declaringClass":"io.cucumber.core.runner.PickleStepDefinitionMatch","methodName":"runStep","fileName":"PickleStepDefinitionMatch.java","lineNumber":63},{"declaringClass":"io.cucumber.core.runner.TestStep","methodName":"executeStep","fileName":"TestStep.java","lineNumber":85},{"declaringClass":"io.cucumber.core.runner.TestStep","methodName":"run","fileName":"TestStep.java","lineNumber":57},{"declaringClass":"io.cucumber.core.runner.PickleStepTestStep","methodName":"run","fileName":"PickleStepTestStep.java","lineNumber":51},{"declaringClass":"io.cucumber.core.runner.TestCase","methodName":"run","fileName":"TestCase.java","lineNumber":84},{"declaringClass":"io.cucumber.core.runner.Runner","methodName":"runPickle","fileName":"Runner.java","lineNumber":75},{"declaringClass":"io.cucumber.core.runtime.CucumberExecutionContext","methodName":"lambda$runTestCase$5","fileName":"CucumberExecutionContext.java","lineNumber":129},{"declaringClass":"io.cucumber.core.runtime.RethrowingThrowableCollector","methodName":"executeAndThrow","fileName":"RethrowingThrowableCollector.java","lineNumber":23},{"declaringClass":"io.cucumber.core.runtime.CucumberExecutionContext","methodName":"runTestCase","fileName":"CucumberExecutionContext.java","lineNumber":129},{"declaringClass":"io.cucumber.junit.FeatureRunner","methodName":"runChild","fileName":"FeatureRunner.java","lineNumber":144},{"declaringClass":"io.cucumber.junit.FeatureRunner","methodName":"runChild","fileName":"FeatureRunner.java","lineNumber":28},{"declaringClass":"io.cucumber.junit.FeatureRunner","methodName":"run","fileName":"FeatureRunner.java","lineNumber":137},{"declaringClass":"io.cucumber.junit.CucumberSerenityRunner","methodName":"runChild","fileName":"CucumberSerenityRunner.java","lineNumber":259},{"declaringClass":"io.cucumber.junit.CucumberSerenityRunner","methodName":"runChild","fileName":"CucumberSerenityRunner.java","lineNumber":59},{"declaringClass":"worker.org.gradle.process.internal.worker.GradleWorkerMain","methodName":"run","fileName":"GradleWorkerMain.java","lineNumber":69},{"declaringClass":"worker.org.gradle.process.internal.worker.GradleWorkerMain","methodName":"main","fileName":"GradleWorkerMain.java","lineNumber":74}],"rootCause":{"errorType":"net.thucydides.core.webdriver.DriverConfigurationError","message":"WebDriver was unable to create a new instance of type class org.openqa.selenium.chrome.ChromeDriver\r\nWebDriver reported the following message: Unable to establish websocket connection to http://localhost:52691/devtools/browser/443065ce-5e7f-46f9-9547-7b68167a7026\nBuild info: version: \u00274.7.1\u0027, revision: \u0027c6795baf1a3\u0027\nSystem info: os.name: \u0027Windows 10\u0027, os.arch: \u0027amd64\u0027, os.version: \u002710.0\u0027, java.version: \u002717.0.2\u0027\nDriver info: driver.version: ChromeDriver\r\nSee below for more details.","stackTrace":[{"declaringClass":"iteractions.NavigateTo","methodName":"performAs","fileName":"NavigateTo.java","lineNumber":16},{"declaringClass":"stepdefinitions.GoogleSearchStepDefinition","methodName":"theUserOpenTheURL","fileName":"GoogleSearchStepDefinition.java","lineNumber":25},{"declaringClass":"io.cucumber.java.Invoker","methodName":"doInvoke","fileName":"Invoker.java","lineNumber":66},{"declaringClass":"io.cucumber.java.Invoker","methodName":"invoke","fileName":"Invoker.java","lineNumber":24},{"declaringClass":"io.cucumber.java.AbstractGlueDefinition","methodName":"invokeMethod","fileName":"AbstractGlueDefinition.java","lineNumber":47},{"declaringClass":"io.cucumber.java.JavaStepDefinition","methodName":"execute","fileName":"JavaStepDefinition.java","lineNumber":29},{"declaringClass":"io.cucumber.core.runner.CoreStepDefinition","methodName":"execute","fileName":"CoreStepDefinition.java","lineNumber":66},{"declaringClass":"io.cucumber.core.runner.PickleStepDefinitionMatch","methodName":"runStep","fileName":"PickleStepDefinitionMatch.java","lineNumber":63},{"declaringClass":"io.cucumber.core.runner.TestStep","methodName":"executeStep","fileName":"TestStep.java","lineNumber":85},{"declaringClass":"io.cucumber.core.runner.TestStep","methodName":"run","fileName":"TestStep.java","lineNumber":57},{"declaringClass":"io.cucumber.core.runner.PickleStepTestStep","methodName":"run","fileName":"PickleStepTestStep.java","lineNumber":51},{"declaringClass":"io.cucumber.core.runner.TestCase","methodName":"run","fileName":"TestCase.java","lineNumber":84},{"declaringClass":"io.cucumber.core.runner.Runner","methodName":"runPickle","fileName":"Runner.java","lineNumber":75},{"declaringClass":"io.cucumber.core.runtime.CucumberExecutionContext","methodName":"lambda$runTestCase$5","fileName":"CucumberExecutionContext.java","lineNumber":129},{"declaringClass":"io.cucumber.core.runtime.RethrowingThrowableCollector","methodName":"executeAndThrow","fileName":"RethrowingThrowableCollector.java","lineNumber":23},{"declaringClass":"io.cucumber.core.runtime.CucumberExecutionContext","methodName":"runTestCase","fileName":"CucumberExecutionContext.java","lineNumber":129},{"declaringClass":"io.cucumber.junit.FeatureRunner","methodName":"runChild","fileName":"FeatureRunner.java","lineNumber":144},{"declaringClass":"io.cucumber.junit.FeatureRunner","methodName":"runChild","fileName":"FeatureRunner.java","lineNumber":28},{"declaringClass":"io.cucumber.junit.FeatureRunner","methodName":"run","fileName":"FeatureRunner.java","lineNumber":137},{"declaringClass":"io.cucumber.junit.CucumberSerenityRunner","methodName":"runChild","fileName":"CucumberSerenityRunner.java","lineNumber":259},{"declaringClass":"io.cucumber.junit.CucumberSerenityRunner","methodName":"runChild","fileName":"CucumberSerenityRunner.java","lineNumber":59},{"declaringClass":"worker.org.gradle.process.internal.worker.GradleWorkerMain","methodName":"run","fileName":"GradleWorkerMain.java","lineNumber":69},{"declaringClass":"worker.org.gradle.process.internal.worker.GradleWorkerMain","methodName":"main","fileName":"GradleWorkerMain.java","lineNumber":74}],"rootCause":{"errorType":"org.openqa.selenium.remote.http.ConnectionFailedException","message":"Unable to establish websocket connection to http://localhost:52691/devtools/browser/443065ce-5e7f-46f9-9547-7b68167a7026\nBuild info: version: \u00274.7.1\u0027, revision: \u0027c6795baf1a3\u0027\nSystem info: os.name: \u0027Windows 10\u0027, os.arch: \u0027amd64\u0027, os.version: \u002710.0\u0027, java.version: \u002717.0.2\u0027\nDriver info: driver.version: ChromeDriver","stackTrace":[{"declaringClass":"iteractions.NavigateTo","methodName":"performAs","fileName":"NavigateTo.java","lineNumber":16},{"declaringClass":"stepdefinitions.GoogleSearchStepDefinition","methodName":"theUserOpenTheURL","fileName":"GoogleSearchStepDefinition.java","lineNumber":25},{"declaringClass":"io.cucumber.java.Invoker","methodName":"doInvoke","fileName":"Invoker.java","lineNumber":66},{"declaringClass":"io.cucumber.java.Invoker","methodName":"invoke","fileName":"Invoker.java","lineNumber":24},{"declaringClass":"io.cucumber.java.AbstractGlueDefinition","methodName":"invokeMethod","fileName":"AbstractGlueDefinition.java","lineNumber":47},{"declaringClass":"io.cucumber.java.JavaStepDefinition","methodName":"execute","fileName":"JavaStepDefinition.java","lineNumber":29},{"declaringClass":"io.cucumber.core.runner.CoreStepDefinition","methodName":"execute","fileName":"CoreStepDefinition.java","lineNumber":66},{"declaringClass":"io.cucumber.core.runner.PickleStepDefinitionMatch","methodName":"runStep","fileName":"PickleStepDefinitionMatch.java","lineNumber":63},{"declaringClass":"io.cucumber.core.runner.TestStep","methodName":"executeStep","fileName":"TestStep.java","lineNumber":85},{"declaringClass":"io.cucumber.core.runner.TestStep","methodName":"run","fileName":"TestStep.java","lineNumber":57},{"declaringClass":"io.cucumber.core.runner.PickleStepTestStep","methodName":"run","fileName":"PickleStepTestStep.java","lineNumber":51},{"declaringClass":"io.cucumber.core.runner.TestCase","methodName":"run","fileName":"TestCase.java","lineNumber":84},{"declaringClass":"io.cucumber.core.runner.Runner","methodName":"runPickle","fileName":"Runner.java","lineNumber":75},{"declaringClass":"io.cucumber.core.runtime.CucumberExecutionContext","methodName":"lambda$runTestCase$5","fileName":"CucumberExecutionContext.java","lineNumber":129},{"declaringClass":"io.cucumber.core.runtime.RethrowingThrowableCollector","methodName":"executeAndThrow","fileName":"RethrowingThrowableCollector.java","lineNumber":23},{"declaringClass":"io.cucumber.core.runtime.CucumberExecutionContext","methodName":"runTestCase","fileName":"CucumberExecutionContext.java","lineNumber":129},{"declaringClass":"io.cucumber.junit.FeatureRunner","methodName":"runChild","fileName":"FeatureRunner.java","lineNumber":144},{"declaringClass":"io.cucumber.junit.FeatureRunner","methodName":"runChild","fileName":"FeatureRunner.java","lineNumber":28},{"declaringClass":"io.cucumber.junit.FeatureRunner","methodName":"run","fileName":"FeatureRunner.java","lineNumber":137},{"declaringClass":"io.cucumber.junit.CucumberSerenityRunner","methodName":"runChild","fileName":"CucumberSerenityRunner.java","lineNumber":259},{"declaringClass":"io.cucumber.junit.CucumberSerenityRunner","methodName":"runChild","fileName":"CucumberSerenityRunner.java","lineNumber":59},{"declaringClass":"worker.org.gradle.process.internal.worker.GradleWorkerMain","methodName":"run","fileName":"GradleWorkerMain.java","lineNumber":69},{"declaringClass":"worker.org.gradle.process.internal.worker.GradleWorkerMain","methodName":"main","fileName":"GradleWorkerMain.java","lineNumber":74}]}}},"result":"ERROR","precondition":false,"level":1}]},{"number":3,"description":"When the user search \"Home\" in google","duration":8,"startTime":"2024-04-03T07:50:24.579149100-05:00[America/Bogota]","result":"SKIPPED","precondition":false,"level":0},{"number":4,"description":"Then the user should see \"Home\" in the result","duration":7,"startTime":"2024-04-03T07:50:24.588775100-05:00[America/Bogota]","result":"SKIPPED","precondition":false,"level":0}],"userStory":{"id":"validate-the-google-search-engine","storyName":"validate the google search engine","displayName":"validate the google search engine","path":"google_search.feature","type":"feature","qualifiedTag":{"name":"validate the google search engine","type":"feature","displayName":"validate the google search engine"}},"featureTag":{"name":"validate the google search engine","type":"feature","displayName":"validate the google search engine"},"title":"Search in google","description":"","tags":[{"name":"validate the google search engine","type":"feature","displayName":"validate the google search engine"}],"allTags":[{"name":"validate the google search engine","type":"feature","displayName":"validate the google search engine"}],"startTime":"2024-04-03T07:50:21.106689100-05:00[America/Bogota]","duration":3499,"testFailureCause":{"errorType":"net.thucydides.core.webdriver.DriverConfigurationError","message":"WebDriver was unable to create a new instance of type class org.openqa.selenium.chrome.ChromeDriver\r\nWebDriver reported the following message: Unable to establish websocket connection to http://localhost:52691/devtools/browser/443065ce-5e7f-46f9-9547-7b68167a7026\nBuild info: version: \u00274.7.1\u0027, revision: \u0027c6795baf1a3\u0027\nSystem info: os.name: \u0027Windows 10\u0027, os.arch: \u0027amd64\u0027, os.version: \u002710.0\u0027, java.version: \u002717.0.2\u0027\nDriver info: driver.version: ChromeDriver\r\nSee below for more details.","stackTrace":[{"declaringClass":"iteractions.NavigateTo","methodName":"performAs","fileName":"NavigateTo.java","lineNumber":16},{"declaringClass":"stepdefinitions.GoogleSearchStepDefinition","methodName":"theUserOpenTheURL","fileName":"GoogleSearchStepDefinition.java","lineNumber":25},{"declaringClass":"io.cucumber.java.Invoker","methodName":"doInvoke","fileName":"Invoker.java","lineNumber":66},{"declaringClass":"io.cucumber.java.Invoker","methodName":"invoke","fileName":"Invoker.java","lineNumber":24},{"declaringClass":"io.cucumber.java.AbstractGlueDefinition","methodName":"invokeMethod","fileName":"AbstractGlueDefinition.java","lineNumber":47},{"declaringClass":"io.cucumber.java.JavaStepDefinition","methodName":"execute","fileName":"JavaStepDefinition.java","lineNumber":29},{"declaringClass":"io.cucumber.core.runner.CoreStepDefinition","methodName":"execute","fileName":"CoreStepDefinition.java","lineNumber":66},{"declaringClass":"io.cucumber.core.runner.PickleStepDefinitionMatch","methodName":"runStep","fileName":"PickleStepDefinitionMatch.java","lineNumber":63},{"declaringClass":"io.cucumber.core.runner.TestStep","methodName":"executeStep","fileName":"TestStep.java","lineNumber":85},{"declaringClass":"io.cucumber.core.runner.TestStep","methodName":"run","fileName":"TestStep.java","lineNumber":57},{"declaringClass":"io.cucumber.core.runner.PickleStepTestStep","methodName":"run","fileName":"PickleStepTestStep.java","lineNumber":51},{"declaringClass":"io.cucumber.core.runner.TestCase","methodName":"run","fileName":"TestCase.java","lineNumber":84},{"declaringClass":"io.cucumber.core.runner.Runner","methodName":"runPickle","fileName":"Runner.java","lineNumber":75},{"declaringClass":"io.cucumber.core.runtime.CucumberExecutionContext","methodName":"lambda$runTestCase$5","fileName":"CucumberExecutionContext.java","lineNumber":129},{"declaringClass":"io.cucumber.core.runtime.RethrowingThrowableCollector","methodName":"executeAndThrow","fileName":"RethrowingThrowableCollector.java","lineNumber":23},{"declaringClass":"io.cucumber.core.runtime.CucumberExecutionContext","methodName":"runTestCase","fileName":"CucumberExecutionContext.java","lineNumber":129},{"declaringClass":"io.cucumber.junit.FeatureRunner","methodName":"runChild","fileName":"FeatureRunner.java","lineNumber":144},{"declaringClass":"io.cucumber.junit.FeatureRunner","methodName":"runChild","fileName":"FeatureRunner.java","lineNumber":28},{"declaringClass":"io.cucumber.junit.FeatureRunner","methodName":"run","fileName":"FeatureRunner.java","lineNumber":137},{"declaringClass":"io.cucumber.junit.CucumberSerenityRunner","methodName":"runChild","fileName":"CucumberSerenityRunner.java","lineNumber":259},{"declaringClass":"io.cucumber.junit.CucumberSerenityRunner","methodName":"runChild","fileName":"CucumberSerenityRunner.java","lineNumber":59},{"declaringClass":"worker.org.gradle.process.internal.worker.GradleWorkerMain","methodName":"run","fileName":"GradleWorkerMain.java","lineNumber":69},{"declaringClass":"worker.org.gradle.process.internal.worker.GradleWorkerMain","methodName":"main","fileName":"GradleWorkerMain.java","lineNumber":74}],"rootCause":{"errorType":"org.openqa.selenium.remote.http.ConnectionFailedException","message":"Unable to establish websocket connection to http://localhost:52691/devtools/browser/443065ce-5e7f-46f9-9547-7b68167a7026\nBuild info: version: \u00274.7.1\u0027, revision: \u0027c6795baf1a3\u0027\nSystem info: os.name: \u0027Windows 10\u0027, os.arch: \u0027amd64\u0027, os.version: \u002710.0\u0027, java.version: \u002717.0.2\u0027\nDriver info: driver.version: ChromeDriver","stackTrace":[{"declaringClass":"iteractions.NavigateTo","methodName":"performAs","fileName":"NavigateTo.java","lineNumber":16},{"declaringClass":"stepdefinitions.GoogleSearchStepDefinition","methodName":"theUserOpenTheURL","fileName":"GoogleSearchStepDefinition.java","lineNumber":25},{"declaringClass":"io.cucumber.java.Invoker","methodName":"doInvoke","fileName":"Invoker.java","lineNumber":66},{"declaringClass":"io.cucumber.java.Invoker","methodName":"invoke","fileName":"Invoker.java","lineNumber":24},{"declaringClass":"io.cucumber.java.AbstractGlueDefinition","methodName":"invokeMethod","fileName":"AbstractGlueDefinition.java","lineNumber":47},{"declaringClass":"io.cucumber.java.JavaStepDefinition","methodName":"execute","fileName":"JavaStepDefinition.java","lineNumber":29},{"declaringClass":"io.cucumber.core.runner.CoreStepDefinition","methodName":"execute","fileName":"CoreStepDefinition.java","lineNumber":66},{"declaringClass":"io.cucumber.core.runner.PickleStepDefinitionMatch","methodName":"runStep","fileName":"PickleStepDefinitionMatch.java","lineNumber":63},{"declaringClass":"io.cucumber.core.runner.TestStep","methodName":"executeStep","fileName":"TestStep.java","lineNumber":85},{"declaringClass":"io.cucumber.core.runner.TestStep","methodName":"run","fileName":"TestStep.java","lineNumber":57},{"declaringClass":"io.cucumber.core.runner.PickleStepTestStep","methodName":"run","fileName":"PickleStepTestStep.java","lineNumber":51},{"declaringClass":"io.cucumber.core.runner.TestCase","methodName":"run","fileName":"TestCase.java","lineNumber":84},{"declaringClass":"io.cucumber.core.runner.Runner","methodName":"runPickle","fileName":"Runner.java","lineNumber":75},{"declaringClass":"io.cucumber.core.runtime.CucumberExecutionContext","methodName":"lambda$runTestCase$5","fileName":"CucumberExecutionContext.java","lineNumber":129},{"declaringClass":"io.cucumber.core.runtime.RethrowingThrowableCollector","methodName":"executeAndThrow","fileName":"RethrowingThrowableCollector.java","lineNumber":23},{"declaringClass":"io.cucumber.core.runtime.CucumberExecutionContext","methodName":"runTestCase","fileName":"CucumberExecutionContext.java","lineNumber":129},{"declaringClass":"io.cucumber.junit.FeatureRunner","methodName":"runChild","fileName":"FeatureRunner.java","lineNumber":144},{"declaringClass":"io.cucumber.junit.FeatureRunner","methodName":"runChild","fileName":"FeatureRunner.java","lineNumber":28},{"declaringClass":"io.cucumber.junit.FeatureRunner","methodName":"run","fileName":"FeatureRunner.java","lineNumber":137},{"declaringClass":"io.cucumber.junit.CucumberSerenityRunner","methodName":"runChild","fileName":"CucumberSerenityRunner.java","lineNumber":259},{"declaringClass":"io.cucumber.junit.CucumberSerenityRunner","methodName":"runChild","fileName":"CucumberSerenityRunner.java","lineNumber":59},{"declaringClass":"worker.org.gradle.process.internal.worker.GradleWorkerMain","methodName":"run","fileName":"GradleWorkerMain.java","lineNumber":69},{"declaringClass":"worker.org.gradle.process.internal.worker.GradleWorkerMain","methodName":"main","fileName":"GradleWorkerMain.java","lineNumber":74}]}},"testFailureClassname":"net.thucydides.core.webdriver.DriverConfigurationError","testFailureMessage":"Could not instantiate class org.openqa.selenium.chrome.ChromeDriver","testFailureSummary":"ERROR;net.thucydides.core.webdriver.DriverConfigurationError;WebDriver was unable to create a new instance of type class org.openqa.selenium.chrome.ChromeDriver\r\nWebDriver reported the following message: Unable to establish websocket connection to http://localhost:52691/devtools/browser/443065ce-5e7f-46f9-9547-7b68167a7026\nBuild info: version: \u00274.7.1\u0027, revision: \u0027c6795baf1a3\u0027\nSystem info: os.name: \u0027Windows 10\u0027, os.arch: \u0027amd64\u0027, os.version: \u002710.0\u0027, java.version: \u002717.0.2\u0027\nDriver info: driver.version: ChromeDriver\r\nSee below for more details.;NavigateTo.java","projectKey":"","annotatedResult":"ERROR","isManualTestingUpToDate":false,"context":"chrome,windows","manual":false,"testSource":"Cucumber","actors":[{"name":"User","can":["browse the web"]}],"result":"ERROR"}